sii_agent_sdk/__init__.py
sii_agent_sdk/bridge.py
sii_agent_sdk/errors.py
sii_agent_sdk/query.py
sii_agent_sdk/session.py
sii_agent_sdk/session_state.py
sii_agent_sdk/types.py
sii_agent_sdk/_internal/__init__.py
sii_agent_sdk/_internal/event_logger.py
sii_agent_sdk/_internal/message_parser.py
sii_agent_sdk-0.1.10.dist-info/licenses/LICENSE
sii_agent_sdk-0.1.10.dist-info/METADATA
sii_agent_sdk-0.1.10.dist-info/WHEEL
sii_agent_sdk-0.1.10.dist-info/top_level.txt
sii_agent_sdk-0.1.10.dist-info/RECORD
