Metadata-Version: 2.4
Name: sii-agent-sdk
Version: 0.1.10
Summary: Python SDK for SII-CLI - AI Agent Framework
Author-email: GAIR-NLP <snowy2002@sjtu.edu.cn>
License: Apache-2.0
Project-URL: Homepage, https://github.com/GAIR-NLP/sii-cli
Project-URL: Documentation, https://github.com/GAIR-NLP/sii-cli/tree/main/packages/python-sdk
Project-URL: Repository, https://github.com/GAIR-NLP/sii-cli
Project-URL: Issues, https://github.com/GAIR-NLP/sii-cli/issues
Keywords: ai,agent,sii,gemini,assistant
Classifier: Development Status :: 3 - Alpha
Classifier: Intended Audience :: Developers
Classifier: License :: OSI Approved :: Apache Software License
Classifier: Programming Language :: Python :: 3
Classifier: Programming Language :: Python :: 3.10
Classifier: Programming Language :: Python :: 3.11
Classifier: Programming Language :: Python :: 3.12
Classifier: Topic :: Scientific/Engineering :: Artificial Intelligence
Requires-Python: >=3.10
License-File: LICENSE
Requires-Dist: anyio>=4.0.0
Provides-Extra: dev
Requires-Dist: pytest>=7.0.0; extra == "dev"
Requires-Dist: pytest-asyncio>=0.21.0; extra == "dev"
Requires-Dist: pytest-cov>=4.0.0; extra == "dev"
Requires-Dist: black>=23.0.0; extra == "dev"
Requires-Dist: mypy>=1.0.0; extra == "dev"
Requires-Dist: ruff>=0.1.0; extra == "dev"
Dynamic: license-file
